[{"name":"sql.active_record","payload":{"sql":"              SELECT a.attname, format_type(a.atttypid, a.atttypmod),\n                     pg_get_expr(d.adbin, d.adrelid), a.attnotnull, a.atttypid, a.atttypmod\n                FROM pg_attribute a LEFT JOIN pg_attrdef d\n                  ON a.attrelid = d.adrelid AND a.attnum = d.adnum\n               WHERE a.attrelid = '\"users\"'::regclass\n                 AND a.attnum \u003E 0 AND NOT a.attisdropped\n               ORDER BY a.attnum\n","name":"SCHEMA","connection_id":70297031065300,"binds":[],"line":8,"filename":"/Users/CarolynNguyen/Documents/GA_projects/Project4-Makeup_File/makeupshadeguide/app/controllers/users_controller.rb","method":"new"},"time":"2014-09-23T13:28:28-07:00","transaction_id":"08f900d38351cf928d0c","end":"2014-09-23T13:28:28-07:00","children":[],"duration":1.338},{"name":"sql.active_record","payload":{"sql":"              SELECT COUNT(*)\n              FROM pg_class c\n              LEFT JOIN pg_namespace n ON n.oid = c.relnamespace\n              WHERE c.relkind in ('v','r')\n              AND c.relname = 'users'\n              AND n.nspname = ANY (current_schemas(false))\n","name":"SCHEMA","connection_id":70297031065300,"binds":[],"line":8,"filename":"/Users/CarolynNguyen/Documents/GA_projects/Project4-Makeup_File/makeupshadeguide/app/controllers/users_controller.rb","method":"new"},"time":"2014-09-23T13:28:28-07:00","transaction_id":"08f900d38351cf928d0c","end":"2014-09-23T13:28:28-07:00","children":[],"duration":0.54},{"name":"sql.active_record","payload":{"sql":"            SELECT attr.attname\n            FROM pg_attribute attr\n            INNER JOIN pg_constraint cons ON attr.attrelid = cons.conrelid AND attr.attnum = cons.conkey[1]\n            WHERE cons.contype = 'p'\n              AND cons.conrelid = '\"users\"'::regclass\n","name":"SCHEMA","connection_id":70297031065300,"binds":[],"line":8,"filename":"/Users/CarolynNguyen/Documents/GA_projects/Project4-Makeup_File/makeupshadeguide/app/controllers/users_controller.rb","method":"new"},"time":"2014-09-23T13:28:28-07:00","transaction_id":"08f900d38351cf928d0c","end":"2014-09-23T13:28:28-07:00","children":[],"duration":0.507},{"name":"sql.active_record","payload":{"sql":"              SELECT a.attname, format_type(a.atttypid, a.atttypmod),\n                     pg_get_expr(d.adbin, d.adrelid), a.attnotnull, a.atttypid, a.atttypmod\n                FROM pg_attribute a LEFT JOIN pg_attrdef d\n                  ON a.attrelid = d.adrelid AND a.attnum = d.adnum\n               WHERE a.attrelid = '\"user_makeups\"'::regclass\n                 AND a.attnum \u003E 0 AND NOT a.attisdropped\n               ORDER BY a.attnum\n","name":"SCHEMA","connection_id":70297031065300,"binds":[],"line":9,"filename":"/Users/CarolynNguyen/Documents/GA_projects/Project4-Makeup_File/makeupshadeguide/app/controllers/users_controller.rb","method":"new"},"time":"2014-09-23T13:28:28-07:00","transaction_id":"08f900d38351cf928d0c","end":"2014-09-23T13:28:28-07:00","children":[],"duration":1.0679999999999998},{"name":"sql.active_record","payload":{"sql":"              SELECT COUNT(*)\n              FROM pg_class c\n              LEFT JOIN pg_namespace n ON n.oid = c.relnamespace\n              WHERE c.relkind in ('v','r')\n              AND c.relname = 'user_makeups'\n              AND n.nspname = ANY (current_schemas(false))\n","name":"SCHEMA","connection_id":70297031065300,"binds":[],"line":9,"filename":"/Users/CarolynNguyen/Documents/GA_projects/Project4-Makeup_File/makeupshadeguide/app/controllers/users_controller.rb","method":"new"},"time":"2014-09-23T13:28:28-07:00","transaction_id":"08f900d38351cf928d0c","end":"2014-09-23T13:28:28-07:00","children":[],"duration":0.602},{"name":"sql.active_record","payload":{"sql":"            SELECT attr.attname\n            FROM pg_attribute attr\n            INNER JOIN pg_constraint cons ON attr.attrelid = cons.conrelid AND attr.attnum = cons.conkey[1]\n            WHERE cons.contype = 'p'\n              AND cons.conrelid = '\"user_makeups\"'::regclass\n","name":"SCHEMA","connection_id":70297031065300,"binds":[],"line":9,"filename":"/Users/CarolynNguyen/Documents/GA_projects/Project4-Makeup_File/makeupshadeguide/app/controllers/users_controller.rb","method":"new"},"time":"2014-09-23T13:28:28-07:00","transaction_id":"08f900d38351cf928d0c","end":"2014-09-23T13:28:28-07:00","children":[],"duration":0.48899999999999993},{"name":"sql.active_record","payload":{"sql":"SELECT \"makeups\".* FROM \"makeups\"","name":"Makeup Load","connection_id":70297031065300,"binds":[],"line":24,"filename":"/Users/CarolynNguyen/Documents/GA_projects/Project4-Makeup_File/makeupshadeguide/app/views/users/new.html.erb","method":"block (2 levels) in _app_views_users_new_html_erb__330785124108466189_70297111632980"},"time":"2014-09-23T13:28:28-07:00","transaction_id":"08f900d38351cf928d0c","end":"2014-09-23T13:28:28-07:00","children":[],"duration":0.941},{"name":"render_template.action_view","payload":{"identifier":"/Users/CarolynNguyen/Documents/GA_projects/Project4-Makeup_File/makeupshadeguide/app/views/users/new.html.erb","layout":"layouts/application"},"time":"2014-09-23T13:28:28-07:00","transaction_id":"cf1338c570f30bbcce72","end":"2014-09-23T13:28:28-07:00","children":[],"duration":18.494},{"name":"process_action.action_controller","payload":{"controller":"UsersController","action":"new","params":{"action":"new","controller":"users"},"format":"html","method":"GET","path":"/users/new","status":200,"view_runtime":26.991,"db_runtime":5.073},"time":"2014-09-23T13:28:28-07:00","transaction_id":"cf1338c570f30bbcce72","end":"2014-09-23T13:28:28-07:00","children":[],"duration":71.46900000000001}]